{
	"C2S_ActionRequest": "0x00a7",
	"C2S_ActionRequestGroundTargeted": "0x0065",
	"Common_UseOodleTcp": true,
	"PatchCode": [],
	"S2C_ActionEffect01": "0x0354",
	"S2C_ActionEffect08": "0x018f",
	"S2C_ActionEffect16": "0x038f",
	"S2C_ActionEffect24": "0x00d1",
	"S2C_ActionEffect32": "0x0340",
	"S2C_ActorCast": "0x00c8",
	"S2C_ActorControl": "0x00d4",
	"S2C_ActorControlSelf": "0x03c1",
	"Server_IpRange": "124.150.157.0/24, 153.254.80.0/24, 202.67.52.0/24, 204.2.29.0/24, 80.239.145.0/24",
	"Server_PortRange": "1025-65535"
}