{
  "name": "Final Fantasy XIV - 5.5 - Death Unto Dawn",
  "searchDirectories": {
    "Death Unto Dawn": {
      "default": true,
      "purchaseLinks": {
        "amazon.co.jp": "https://www.amazon.co.jp/dp/B097XB7DD6/"
      }
    }
  },
  "items": [
    {
      "source": [
        "00000",
        "DUD_001",
        "ローカス \\(Duality\\) ～機工城アレキサンダー：起動編～",
        "Locus \\(Duality\\)"
      ],
      "target": {
        "path": "music/ex3/BGM_EX3_Boss_Battle02.scd"
      }
    },
    {
      "source": [
        "00001",
        "DUD_002",
        "メタル：ブルートジャスティスモード \\(Journeys\\) ～機工城アレキサンダー：律動編～",
        "Metal - Brute Justice Mode \\(Journeys\\)"
      ],
      "target": {
        "path": "music/ex3/BGM_EX3_Ban_05.scd",
        "segments": [
          {
            "channels": [
              {
                "source": "source",
                "channel": 0
              },
              {
                "source": "source",
                "channel": 1
              }
            ],
            "length": 205.5
          },
          {
            "sourceOffsets": {
              "target": 205.5
            },
            "channels": [
              {
                "source": "target",
                "channel": 0
              },
              {
                "source": "target",
                "channel": 1
              }
            ]
          }
        ],
        "# comment": [
          "Fall back to in-game version's loop, instead of blu-ray disc's version with ending.",
          "Technically, we can reuse the silencing part at the mid of the song, but using that requires figuring out exact timestamp of the section to take."
        ]
      }
    },
    {
      "source": [
        "00002",
        "DUD_003",
        "ライズ \\(Journeys\\) ～機工城アレキサンダー：天動編～",
        "Rise \\(Journeys\\)"
      ],
      "target": [
        {
          "path": "music/ffxiv/Orchestrion/BGM_ORCH_285.scd"
        },
        {
          "path": "music/ex3/BGM_EX3_Ban_07.scd",
          "segments": [
            {
              "channels": [
                {
                  "source": "source",
                  "channel": 0
                },
                {
                  "source": "source",
                  "channel": 1
                },
                {
                  "source": "target",
                  "channel": 2
                },
                {
                  "source": "target",
                  "channel": 3
                }
              ]
            }
          ],
          "enable": false,
          "# comment": [
            "In-game Statis Loop has longer repeat cycle than blu-ray version.",
            "Blu-ray version has stasis loop in it, which will delay the remainder of the song; will probably need sample block index adjustment"
          ]
        }
      ]
    },
    {
      "source": [
        "00003",
        "DUD_004",
        "メビウス \\(Orchestral Version\\) ～機工城アレキサンダー：天動編～",
        "Moebius \\(Orchestral Version\\)"
      ],
      "target": [
        {
          "path": "music/ffxiv/Orchestrion/BGM_ORCH_314.scd",
          "enable": false
        },
        {
          "path": "music/ex3/BGM_EX3_Ban_08.scd",
          "enable": false,
          "# comment": "Blu-ray version has statis loop-esque sequence in it, rendering it incompatible with in-game resource."
        }
      ]
    },
    {
      "source": {
        "A Fine Air Forbiddeth": [
          "00004",
          "DUD_005",
          "戦士の守勢 ～PvPフロントライン～",
          "A Fine Air Forbiddeth"
        ],
        "A Fierce Air Forceth": [
          "00005",
          "DUD_006",
          "戦士の攻勢 ～PvPフロントライン～",
          "A Fierce Air Forceth"
        ]
      },
      "target": [
        {
          "path": "music/ffxiv/BGM_PvP_Battle_02.scd",
          "sequentialToFfmpegChannelIndexMap": [
            0,
            2,
            1,
            4,
            5,
            3
          ],
          "segments": [
            {
              "channels": [
                {
                  "source": "A Fine Air Forbiddeth",
                  "channel": 0
                },
                {
                  "source": "A Fine Air Forbiddeth",
                  "channel": 1
                },
                {
                  "source": "A Fierce Air Forceth",
                  "channel": 0
                },
                {
                  "source": "A Fierce Air Forceth",
                  "channel": 1
                },
                {
                  "source": "target",
                  "channel": 4
                },
                {
                  "source": "target",
                  "channel": 5
                }
              ]
            }
          ]
        },
        {
          "path": "music/ffxiv/Orchestrion/BGM_ORCH_357.scd",
          "segments": [
            {
              "channels": [
                {
                  "source": "A Fine Air Forbiddeth",
                  "channel": 0
                },
                {
                  "source": "A Fine Air Forbiddeth",
                  "channel": 1
                }
              ]
            }
          ]
        },
        {
          "path": [
            "music/ffxiv/BGM_Ride_Frontline.scd",
            "music/ffxiv/Orchestrion/BGM_ORCH_356.scd"
          ],
          "segments": [
            {
              "channels": [
                {
                  "source": "A Fierce Air Forceth",
                  "channel": 0
                },
                {
                  "source": "A Fierce Air Forceth",
                  "channel": 1
                }
              ]
            }
          ]
        }
      ]
    },
    {
      "source": [
        "00006",
        "DUD_007",
        "リェー・メグの門",
        "The Garden's Gates"
      ],
      "target": {
        "path": [
          "music/ex3/BGM_EX3_BanFort_Fairy_Good.scd",
          "music/ffxiv/Orchestrion/BGM_ORCH_355.scd"
        ]
      }
    },
    {
      "source": [
        "00007",
        "DUD_008",
        "花の館 ～魔法宮殿 グラン・コスモス～",
        "The Grand Cosmos"
      ],
      "target": {
        "path": [
          "music/ex3/BGM_EX3_Dan_D09.scd",
          "music/ffxiv/Orchestrion/BGM_ORCH_354.scd"
        ]
      }
    },
    {
      "source": [
        "00008",
        "DUD_009",
        "名も無き者たちの情熱 ～蒼天街復興～",
        "The Mendicant's Relish"
      ],
      "target": {
        "path": [
          "music/ex1/BGM_EX1_FATE_Hukko.scd",
          "music/ffxiv/Orchestrion/BGM_ORCH_385.scd"
        ]
      }
    },
    {
      "source": {
        "Starlight de Chocobo": [
          "00009",
          "DUD_010",
          "スターライト de チョコボ",
          "Starlight de Chocobo"
        ],
        "Starlight de Chocobo (?)": [
          "00010",
          "DUD_011",
          "スターライト de チョコボ？",
          "Starlight de Chocobo \\(\\?\\)"
        ]
      },
      "target": [
        {
          "path": "music/ffxiv/BGM_Season_XmasCho_02.scd",
          "segments": [
            {
              "channels": [
                {
                  "source": "Starlight de Chocobo",
                  "channel": 0
                },
                {
                  "source": "Starlight de Chocobo",
                  "channel": 1
                },
                {
                  "source": "Starlight de Chocobo (?)",
                  "channel": 0
                },
                {
                  "source": "Starlight de Chocobo (?)",
                  "channel": 1
                }
              ]
            }
          ]
        },
        {
          "path": "music/ffxiv/Orchestrion/BGM_ORCH_358.scd",
          "enable": false,
          "segments": [
            {
              "channels": [
                {
                  "source": "Starlight de Chocobo",
                  "channel": 0
                },
                {
                  "source": "Starlight de Chocobo",
                  "channel": 1
                }
              ]
            }
          ]
        }
      ]
    },
    {
      "source": [
        "00011",
        "DUD_012",
        "意味／無 \\(From NieR:Automata\\)",
        "Significance - Nothing \\(From NieR:Automata\\)"
      ],
      "target": {
        "path": [
          "music/ex3/BGM_EX3_Ytc_01.scd",
          "music/ffxiv/Orchestrion/BGM_ORCH_362.scd"
        ]
      }
    },
    {
      "source": [
        "00012",
        "DUD_013",
        "曖昧ナ希望／氷雨 \\(From NieR:Automata\\)",
        "Vague Hope - Cold Rain \\(From NieR:Automata\\)"
      ],
      "target": {
        "path": "music/ex3/BGM_EX3_Ytc_03.scd"
      }
    },
    {
      "source": [
        "00013",
        "DUD_014",
        "崩壊ノ虚妄 \\(From NieR:Automata\\)",
        "Crumbling Lies - Front \\(From NieR:Automata\\)"
      ],
      "target": {
        "path": [
          "music/ex3/BGM_EX3_Ytc_10.scd",
          "music/ffxiv/Orchestrion/BGM_ORCH_381.scd"
        ]
      }
    },
    {
      "source": [
        "00014",
        "DUD_015",
        "顕現シタ異物 \\(From NieR:Automata\\)",
        "Alien Manifestation \\(From NieR:Automata\\)"
      ],
      "target": {
        "path": [
          "music/ex3/BGM_EX3_Ytc_06.scd",
          "music/ffxiv/Orchestrion/BGM_ORCH_365.scd"
        ]
      }
    },
    {
      "source": [
        "00015",
        "DUD_016",
        "イニシエノウタ／贖罪 \\(From NieR:Automata\\)",
        "Song of the Ancients - Atonement \\(From NieR:Automata\\)"
      ],
      "target": {
        "path": [
          "music/ex3/BGM_EX3_Ytc_07.scd",
          "music/ffxiv/Orchestrion/BGM_ORCH_366.scd"
        ]
      }
    },
    {
      "source": [
        "00016",
        "DUD_017",
        "双極ノ悪夢 \\(From NieR:Automata\\)",
        "Bipolar Nightmare \\(From NieR:Automata\\)"
      ],
      "target": {
        "path": [
          "music/ex3/BGM_EX3_Ytc_08.scd",
          "music/ffxiv/Orchestrion/BGM_ORCH_367.scd"
        ]
      }
    },
    {
      "source": [
        "00017",
        "DUD_018",
        "Weight of the World／Prelude Version",
        "Weight of the World - Prelude Version"
      ],
      "target": {
        "path": [
          "music/ex3/BGM_EX3_Ytc_09.scd",
          "music/ffxiv/Orchestrion/BGM_ORCH_368.scd"
        ]
      }
    },
    {
      "source": [
        "00018",
        "DUD_019",
        "澱ンダ祈リ／暁風 \\(From NieR:Automata\\)",
        "Faltering Prayer - Dawn Breeze \\(From NieR:Automata\\)"
      ],
      "target": {
        "path": [
          "music/ex3/BGM_EX3_Ytc_29.scd",
          "music/ffxiv/Orchestrion/BGM_ORCH_491.scd"
        ]
      }
    },
    {
      "source": [
        "00019",
        "DUD_020",
        "還ラナイ声／ギター \\(From NieR:Automata\\)",
        "Voice of no Return - Guitar \\(From NieR:Automata\\)"
      ],
      "target": {
        "path": [
          "music/ex3/BGM_EX3_Ytc_05.scd",
          "music/ffxiv/Orchestrion/BGM_ORCH_364.scd"
        ]
      }
    },
    {
      "source": [
        "00020",
        "DUD_021",
        "底に潜みし者 ～黒風海底 アニドラス・アナムネーシス～",
        "Floundering in the Depths"
      ],
      "target": {
        "path": [
          "music/ex3/BGM_EX3_Dan_D10.scd",
          "music/ffxiv/Orchestrion/BGM_ORCH_379.scd"
        ]
      }
    },
    {
      "source": [
        "00021",
        "DUD_022",
        "貪欲 \\(Scions & Sinners\\)",
        "Insatiable \\(Scions & Sinners\\)"
      ],
      "target": {
        "path": [
          "music/ex3/BGM_EX3_Boss_Battle03.scd",
          "music/ffxiv/Orchestrion/BGM_ORCH_465.scd"
        ],
        "loopOffsetDelta": 10,
        "# comment": "Blu-ray version has an ending"
      }
    },
    {
      "source": [
        "00022",
        "DUD_023",
        "ホパル古盤",
        "Hopl's Dropple"
      ],
      "target": {
        "path": [
          "music/ex3/BGM_EX3_BanFort_kkrn_Good.scd",
          "music/ffxiv/Orchestrion/BGM_ORCH_380.scd"
        ]
      }
    },
    {
      "source": [
        "00023",
        "DUD_024",
        "究極幻想 \\(Scions & Sinners\\)",
        "Ultima \\(Scions & Sinners\\)"
      ],
      "target": {
        "path": [
          "music/ex3/BGM_EX3_Ban_09.scd",
          "music/ffxiv/BGM_Ride_Ruby.scd",
          "music/ffxiv/Orchestrion/BGM_ORCH_375.scd"
        ],
        "loopOffsetDelta": 7,
        "# comment": "Blu-ray version has an ending"
      }
    },
    {
      "source": [
        "00024",
        "DUD_025",
        "白銀の凶鳥、飛翔せり \\(Orchestral Version\\)",
        "Rise of the White Raven \\(Orchestral Version\\)"
      ],
      "target": {
        "path": "music/ex3/BGM_EX3_Ban_10.scd"
      }
    },
    {
      "source": [
        "00025",
        "DUD_026",
        "蒼き日常 ～蒼天街復興～",
        "Hearthward"
      ],
      "target": {
        "path": [
          "music/ex1/BGM_EX1_Hukko_Finish01.scd",
          "music/ffxiv/BGM_Ride_Hukko01.scd",
          "music/ffxiv/Orchestrion/BGM_ORCH_450.scd"
        ]
      }
    },
    {
      "source": [
        "00026",
        "DUD_027",
        "雷轟電撃 ～希望の園エデン：共鳴編～",
        "Twice Stricken"
      ],
      "target": {
        "path": [
          "music/ex3/BGM_EX3_Raid_05.scd",
          "music/ffxiv/BGM_Ride_Eden02.scd",
          "music/ffxiv/Orchestrion/BGM_ORCH_372.scd"
        ]
      }
    },
    {
      "source": [
        "00027",
        "DUD_028",
        "原始の堕天使 ～希望の園エデン：共鳴編～",
        "Primal Angel"
      ],
      "target": {
        "path": [
          "music/ex3/BGM_EX3_Raid_06.scd",
          "music/ffxiv/Orchestrion/BGM_ORCH_373.scd"
        ]
      }
    },
    {
      "source": [
        "00028",
        "DUD_029",
        "雪上の足跡 ～蛮神シヴァ前哨戦～",
        "Footsteps in the Snow"
      ],
      "target": {
        "path": [
          "music/ffxiv/BGM_Ban_Shiva1.scd",
          "music/ffxiv/Orchestrion/BGM_ORCH_113.scd"
        ]
      }
    },
    {
      "source": [
        "00029",
        "DUD_030",
        "分割された光 ～希望の園エデン：共鳴編～",
        "A Sundering of Light"
      ],
      "target": {
        "path": "music/ex3/BGM_EX3_Raid_08.scd"
      }
    },
    {
      "source": [
        "00030",
        "DUD_031",
        "忘却の此方 ～希望の園エデン：共鳴編～",
        "Return to Oblivion"
      ],
      "target": {
        "path": [
          "music/ex3/BGM_EX3_Raid_07.scd",
          "music/ffxiv/Orchestrion/BGM_ORCH_374.scd"
        ]
      }
    },
    {
      "source": [
        "00031",
        "DUD_032",
        "ガンゴッシュ",
        "Gangos"
      ],
      "target": {
        "path": "music/ex3/BGM_EX3_Event_21.scd"
      }
    },
    {
      "source": {
        "Wind on the Plains": [
          "00032",
          "DUD_033",
          "ボズヤの微風",
          "Wind on the Plains"
        ],
        "Blood on the Wind": [
          "00033",
          "DUD_034",
          "ボズヤの血風",
          "Blood on the Wind"
        ]
      },
      "target": [
        {
          "path": "music/ex3/BGM_EX3_MYC_01.scd",
          "sequentialToFfmpegChannelIndexMap": [
            0,
            2,
            1,
            4,
            5,
            3
          ],
          "segments": [
            {
              "channels": [
                {
                  "source": "Wind on the Plains",
                  "channel": 0
                },
                {
                  "source": "Wind on the Plains",
                  "channel": 1
                },
                {
                  "source": "Blood on the Wind",
                  "channel": 0
                },
                {
                  "source": "Blood on the Wind",
                  "channel": 1
                },
                {
                  "source": "target",
                  "channel": 4
                },
                {
                  "source": "target",
                  "channel": 5
                }
              ]
            }
          ]
        },
        {
          "path": "music/ffxiv/Orchestrion/BGM_ORCH_412.scd",
          "segments": [
            {
              "channels": [
                {
                  "source": "Wind on the Plains",
                  "channel": 0
                },
                {
                  "source": "Wind on the Plains",
                  "channel": 1
                }
              ]
            }
          ]
        },
        {
          "path": "music/ffxiv/Orchestrion/BGM_ORCH_413.scd",
          "segments": [
            {
              "channels": [
                {
                  "source": "Blood on the Wind",
                  "channel": 0
                },
                {
                  "source": "Blood on the Wind",
                  "channel": 1
                }
              ]
            }
          ]
        }
      ]
    },
    {
      "source": [
        "00034",
        "DUD_035",
        "騒乱 \\(Zodiac Age Version\\)",
        "Unrest \\(Zodiac Age Version\\)"
      ],
      "target": {
        "path": [
          "music/ex3/BGM_EX3_MYC_06.scd",
          "music/ffxiv/BGM_Ride_MYC01.scd"
        ],
        "loopLengthDivisor": 2,
        "# comment": "One period contains two loops"
      }
    },
    {
      "source": [
        "00035",
        "DUD_036",
        "動乱 帝国バージョン \\(Zodiac Age Version\\)",
        "Discord: Imperial \\(Zodiac Age Version\\)"
      ],
      "target": {
        "path": [
          "music/ex3/BGM_EX3_MYC_02.scd",
          "music/ffxiv/Orchestrion/BGM_ORCH_414.scd"
        ]
      }
    },
    {
      "source": [
        "00036",
        "DUD_037",
        "潜入 \\(Zodiac Age Version\\)",
        "Into the Fortress \\(Zodiac Age Version\\)"
      ],
      "target": {
        "path": [
          "music/ex3/BGM_EX3_MYC_03.scd",
          "music/ffxiv/Orchestrion/BGM_ORCH_415.scd"
        ]
      }
    },
    {
      "source": [
        "00037",
        "DUD_038",
        "召喚獣戦 \\(Zodiac Age Version\\)",
        "Battle with an Esper \\(Zodiac Age Version\\)"
      ],
      "target": {
        "path": [
          "music/ex3/BGM_EX3_MYC_04.scd",
          "music/ffxiv/Orchestrion/BGM_ORCH_416.scd"
        ],
        "loopOffsetDelta": 80
      }
    },
    {
      "source": [
        "00038",
        "DUD_039",
        "死闘 \\(Zodiac Age Version\\)",
        "Life and Death \\(Zodiac Age Version\\)"
      ],
      "target": {
        "path": [
          "music/ex3/BGM_EX3_MYC_05.scd",
          "music/ffxiv/Orchestrion/BGM_ORCH_417.scd"
        ],
        "loopLengthDivisor": 2,
        "# comment": "One period contains two loops"
      }
    },
    {
      "source": [
        "00039",
        "DUD_040",
        "ワッツハンマー・ガレージ",
        "Watts's Anvil"
      ],
      "target": {
        "path": [
          "music/ex3/BGM_EX3_BanFort_Dwarf_Good.scd",
          "music/ffxiv/Orchestrion/BGM_ORCH_408.scd"
        ]
      }
    },
    {
      "source": [
        "00040",
        "DUD_041",
        "常夏の島",
        "The Isle of Endless Summer"
      ],
      "target": {
        "path": "music/ffxiv/BGM_Event_Hula.scd"
      }
    },
    {
      "source": [
        "00041",
        "DUD_042",
        "すべての道が至る場所 ～漆黒決戦 ノルヴラント～",
        "Where All Roads Lead"
      ],
      "target": {
        "path": [
          "music/ex3/BGM_EX3_Dan_D11.scd",
          "music/ffxiv/Orchestrion/BGM_ORCH_418.scd"
        ]
      }
    },
    {
      "source": [
        "00042",
        "DUD_043",
        "暗がりに響く音",
        "Echoes in the Dark"
      ],
      "target": {
        "path": "music/ex3/BGM_EX3_Ban_12.scd",
        "loopOffsetDelta": 1,
        "segments": [
          {
            "channels": [
              {
                "source": "source",
                "channel": 0
              },
              {
                "source": "source",
                "channel": 1
              }
            ],
            "length": 72
          },
          {
            "sourceOffsets": {
              "target": 72
            },
            "channels": [
              {
                "source": "target",
                "channel": 0
              },
              {
                "source": "target",
                "channel": 1
              }
            ]
          }
        ]
      }
    },
    {
      "source": [
        "00043",
        "DUD_044",
        "To the Edge"
      ],
      "target": {
        "path": [
          "music/ex3/BGM_EX3_Ban_11.scd",
          "music/ffxiv/BGM_Ride_WOL.scd",
          "music/ffxiv/Orchestrion/BGM_ORCH_411.scd"
        ],
        "# comment": "BGM_EX3_Ban_14: intro truncated version",
        "segments": [
          {
            "sourceFilters": {
              "source": "volume=-3dB"
            },
            "channels": [
              {
                "source": "source",
                "channel": 0
              },
              {
                "source": "source",
                "channel": 1
              }
            ],
            "length": 432
          },
          {
            "sourceOffsets": {
              "target": 432
            },
            "channels": [
              {
                "source": "target",
                "channel": 0
              },
              {
                "source": "target",
                "channel": 1
              }
            ]
          }
        ]
      }
    },
    {
      "source": [
        "00044",
        "DUD_045",
        "悠久の風 ～漆黒～",
        "Eternal Wind \\(Shadowbringers\\)"
      ],
      "target": {
        "path": [
          "music/ex3/BGM_EX3_Event_22.scd",
          "music/ffxiv/Orchestrion/BGM_ORCH_410.scd"
        ],
        "segments": [
          {
            "sourceOffsets": {
              "source": 0
            },
            "sourceThresholds": {
              "target": 0.03,
              "source": 0.03
            },
            "channels": [
              {
                "source": "source",
                "channel": 0
              },
              {
                "source": "source",
                "channel": 1
              }
            ]
          }
        ]
      }
    },
    {
      "source": [
        "00045",
        "DUD_046",
        "遊園施設 \\(From NieR:Automata\\)",
        "Amusement Park \\(From NieR:Automata\\)"
      ],
      "target": {
        "path": [
          "music/ex3/BGM_EX3_Ytc_13.scd",
          "music/ffxiv/Orchestrion/BGM_ORCH_425.scd"
        ]
      }
    },
    {
      "source": [
        "00046",
        "DUD_047",
        "偽リノ城塞 \\(From NieR:Automata\\)",
        "Fortress of Lies \\(From NieR:Automata\\)"
      ],
      "target": {
        "path": [
          "music/ex3/BGM_EX3_Ytc_14.scd",
          "music/ffxiv/Orchestrion/BGM_ORCH_426.scd"
        ]
      }
    },
    {
      "source": [
        "00047",
        "DUD_048",
        "オバアチャン／破壊 \\(From NieR:Automata\\)",
        "Grandma - Destruction \\(From NieR:Automata\\)"
      ],
      "target": {
        "path": [
          "music/ex3/BGM_EX3_Ytc_15.scd",
          "music/ffxiv/Orchestrion/BGM_ORCH_427.scd"
        ]
      }
    },
    {
      "source": [
        "00048",
        "DUD_049",
        "異形ノ末路 \\(From NieR:Automata\\)",
        "End of the Unknown \\(From NieR:Automata\\)"
      ],
      "target": {
        "path": [
          "music/ex3/BGM_EX3_Ytc_16.scd",
          "music/ffxiv/Orchestrion/BGM_ORCH_428.scd"
        ]
      }
    },
    {
      "source": [
        "00049",
        "DUD_050",
        "天より降りし力～全テヲ破壊スル黒キ巨人／Medley Version",
        "Torn from the Heavens/The Dark Colossus Destroys All - Medley Version"
      ],
      "target": {
        "path": [
          "music/ex3/BGM_EX3_Ytc_17.scd",
          "music/ffxiv/Orchestrion/BGM_ORCH_429.scd"
        ]
      }
    },
    {
      "source": [
        "00050",
        "DUD_051",
        "割レタ心 \\(From NieR:Automata\\)",
        "Broken Heart \\(From NieR:Automata\\)"
      ],
      "target": {
        "path": [
          "music/ex3/BGM_EX3_Ytc_11.scd",
          "music/ffxiv/Orchestrion/BGM_ORCH_424.scd"
        ]
      }
    },
    {
      "source": {
        "New Foundations": [
          "00051",
          "DUD_052",
          "祝いの調べ ～蒼天街復興～",
          "New Foundations"
        ],
        "New Foundations (Groundbreaking)": [
          "00052",
          "DUD_053",
          "祝いの調べ：熱演 ～蒼天街復興～",
          "New Foundations \\(Groundbreaking\\)"
        ]
      },
      "target": [
        {
          "path": "music/ex1/BGM_EX1_Hukko_concert.scd",
          "segments": [
            {
              "channels": [
                {
                  "source": "New Foundations",
                  "channel": 0
                },
                {
                  "source": "New Foundations",
                  "channel": 1
                },
                {
                  "source": "New Foundations (Groundbreaking)",
                  "channel": 0
                },
                {
                  "source": "New Foundations (Groundbreaking)",
                  "channel": 1
                }
              ]
            }
          ]
        },
        {
          "path": "music/ffxiv/Orchestrion/BGM_ORCH_432.scd",
          "segments": [
            {
              "channels": [
                {
                  "source": "New Foundations",
                  "channel": 0
                },
                {
                  "source": "New Foundations",
                  "channel": 1
                }
              ]
            }
          ]
        }
      ]
    },
    {
      "source": [
        "00053",
        "DUD_054",
        "ゴゴのテーマ",
        "Gogo's Theme"
      ],
      "target": {
        "path": [
          "music/ex2/BGM_EX2_AOZ_Battle03.scd",
          "music/ffxiv/Orchestrion/BGM_ORCH_434.scd"
        ]
      }
    },
    {
      "source": [
        "00055",
        "DUD_055",
        "焼き立てポークシー ～魔術工房 マトーヤのアトリエ～",
        "Freshly Glazed Porxie"
      ],
      "target": {
        "path": [
          "music/ex3/BGM_EX3_Dan_D12.scd",
          "music/ffxiv/Orchestrion/BGM_ORCH_438.scd"
        ]
      }
    },
    {
      "source": [
        "00056",
        "DUD_056",
        "漆黒の王狼、再び ～エメラルドウェポン破壊作戦～",
        "The Black Wolf Stalks Again"
      ],
      "target": {
        "path": [
          "music/ex3/BGM_EX3_Con_01.scd",
          "music/ffxiv/BGM_Ride_Emerald.scd",
          "music/ffxiv/Orchestrion/BGM_ORCH_433.scd"
        ]
      }
    },
    {
      "source": [
        "00057",
        "DUD_057",
        "Don’t be Afraid ～漆黒～",
        "Don't Be Afraid \\(Shadowbringers\\)"
      ],
      "target": {
        "path": [
          "music/ex3/BGM_EX3_Raid_09.scd",
          "music/ffxiv/Orchestrion/BGM_ORCH_439.scd"
        ]
      }
    },
    {
      "source": [
        "00058",
        "DUD_058",
        "The Legendary Beast ～漆黒～",
        "The Legendary Beast \\(Shadowbringers\\)"
      ],
      "target": {
        "path": [
          "music/ex3/BGM_EX3_Raid_10.scd",
          "music/ffxiv/Orchestrion/BGM_ORCH_440.scd"
        ]
      }
    },
    {
      "source": [
        "00059",
        "DUD_059",
        "美しき思い出 ～希望の園エデン：再生編～",
        "Treasured Memory"
      ],
      "target": {
        "path": [
          "music/ex3/BGM_EX3_Event_29.scd",
          "music/ffxiv/Orchestrion/BGM_ORCH_441.scd"
        ]
      }
    },
    {
      "source": [
        "00060",
        "DUD_060",
        "消せない約束 ～希望の園エデン：再生編～",
        "Promises to Keep"
      ],
      "target": {
        "path": [
          "music/ex3/BGM_EX3_Raid_11.scd",
          "music/ffxiv/BGM_Ride_Eden03.scd",
          "music/ffxiv/Orchestrion/BGM_ORCH_442.scd"
        ]
      }
    },
    {
      "source": [
        "00061",
        "DUD_061",
        "The Extreme ～漆黒～",
        "The Extreme \\(Shadowbringers\\)"
      ],
      "target": {
        "path": "music/ex3/BGM_EX3_Raid_12.scd"
      }
    },
    {
      "source": [
        "00062",
        "DUD_062",
        "Ami ～漆黒～",
        "Ami \\(Shadowbringers\\)"
      ],
      "target": {
        "path": "music/ex3/BGM_EX3_Event_20.scd"
      }
    },
    {
      "source": [
        "00063",
        "DUD_063",
        "Shuffle or Boogie ～漆黒～",
        "Shuffle or Boogie \\(Shadowbringers\\)"
      ],
      "target": {
        "path": [
          "music/ffxiv/BGM_GlodSaucer_TripleWaiting.scd",
          "music/ffxiv/Orchestrion/BGM_ORCH_455.scd"
        ],
        "# comment": "\"glod\" is sic"
      }
    },
    {
      "source": [
        "00064",
        "DUD_064",
        "ソーヘン地下宮殿 \\(Zodiac Age Version\\)",
        "The Sochen Cave Palace \\(Zodiac Age Version\\)"
      ],
      "target": {
        "path": [
          "music/ex3/BGM_EX3_MYC_07.scd",
          "music/ffxiv/Orchestrion/BGM_ORCH_435.scd"
        ]
      }
    },
    {
      "source": [
        "00065",
        "DUD_065",
        "言葉無き戦い \\(Zodiac Age Version\\)",
        "Giving Chase \\(Zodiac Age Version\\)"
      ],
      "target": {
        "path": [
          "music/ex3/BGM_EX3_MYC_08.scd",
          "music/ffxiv/Orchestrion/BGM_ORCH_436.scd"
        ]
      }
    },
    {
      "source": [
        "00066",
        "DUD_066",
        "復活の女王 ～グンヒルド・ディルーブラム～",
        "The Queen Awakens"
      ],
      "target": {
        "path": [
          "music/ex3/BGM_EX3_MYC_09.scd",
          "music/ffxiv/Orchestrion/BGM_ORCH_437.scd"
        ]
      }
    },
    {
      "source": [
        "00067",
        "DUD_067",
        "怒れる悪魔 ～旗艦ダル・リアータ攻略戦～",
        "Wrath of the Harrier"
      ],
      "target": {
        "path": [
          "music/ex3/BGM_EX3_MYC_10.scd",
          "music/ffxiv/Orchestrion/BGM_ORCH_472.scd"
        ]
      }
    },
    {
      "source": [
        "00068",
        "DUD_068",
        "蒼天街復興祝祭",
        "Skyrise"
      ],
      "target": {
        "path": [
          "music/ex1/BGM_EX1_Hukko_Fes.scd",
          "music/ffxiv/Orchestrion/BGM_ORCH_473.scd"
        ]
      }
    },
    {
      "source": [
        "00069",
        "DUD_069",
        "還ラナイ声／通常 \\(From NieR:Automata\\)",
        "Voice of no Return - Normal \\(From NieR:Automata\\)"
      ],
      "target": {
        "path": [
          "music/ex3/BGM_EX3_Ytc_25.scd",
          "music/ffxiv/Orchestrion/BGM_ORCH_487.scd"
        ]
      }
    },
    {
      "source": [
        "00070",
        "DUD_070",
        "沈痛ノ色 \\(From NieR:Automata\\)",
        "The Color of Depression \\(From NieR:Automata\\)"
      ],
      "target": {
        "path": [
          "music/ex3/BGM_EX3_Ytc_26.scd",
          "music/ffxiv/Orchestrion/BGM_ORCH_488.scd"
        ],
        "enable": false,
        "# comment": "Incomplete."
      }
    },
    {
      "source": [
        "00071",
        "DUD_071",
        "茫洋タル病 \\(From NieR:Automata\\)",
        "Widespread Illness \\(From NieR:Automata\\)"
      ],
      "target": {
        "path": [
          "music/ex3/BGM_EX3_Ytc_27.scd",
          "music/ffxiv/Orchestrion/BGM_ORCH_489.scd"
        ],
        "enable": false,
        "# comment": "Incomplete."
      }
    },
    {
      "source": [
        "00072",
        "DUD_072",
        "エミール／絶望 \\(From NieR:Automata\\)",
        "Emil - Despair \\(From NieR:Automata\\)"
      ],
      "target": {
        "path": [
          "music/ex3/BGM_EX3_Ytc_19.scd",
          "music/ffxiv/Orchestrion/BGM_ORCH_481.scd"
        ]
      }
    },
    {
      "source": [
        "00073",
        "DUD_073",
        "追悼 \\(From NieR:Automata\\)",
        "Mourning \\(From NieR:Automata\\)"
      ],
      "target": {
        "path": [
          "music/ex3/BGM_EX3_Ytc_18.scd",
          "music/ffxiv/Orchestrion/BGM_ORCH_480.scd"
        ]
      }
    },
    {
      "source": [
        "00074",
        "DUD_074",
        "終ワリノ音 \\(From NieR:Automata\\)",
        "The Sound of the End \\(From NieR:Automata\\)"
      ],
      "target": {
        "path": [
          "music/ex3/BGM_EX3_Ytc_21.scd",
          "music/ffxiv/Orchestrion/BGM_ORCH_483.scd"
        ]
      }
    },
    {
      "source": [
        "00075",
        "DUD_075",
        "終ワリノ音：丁 \\(From NieR:Automata\\)",
        "The Sound of the End: 8bit \\(From NieR:Automata\\)"
      ],
      "target": {
        "path": [
          "music/ex3/BGM_EX3_Ytc_22.scd",
          "music/ffxiv/Orchestrion/BGM_ORCH_484.scd"
        ]
      }
    },
    {
      "source": [
        "00076",
        "DUD_076",
        "取リ憑イタ業病 \\(From NieR:Automata\\)",
        "Possessed by Disease \\(From NieR:Automata\\)"
      ],
      "target": {
        "path": [
          "music/ex3/BGM_EX3_Ytc_28.scd",
          "music/ffxiv/Orchestrion/BGM_ORCH_490.scd"
        ]
      }
    },
    {
      "source": [
        "00077",
        "DUD_077",
        "カイネ／Final Fantasy Main Theme Version",
        "Kainé - Final Fantasy Main Theme Version"
      ],
      "target": {
        "path": [
          "music/ex3/BGM_EX3_Ytc_23.scd",
          "music/ffxiv/Orchestrion/BGM_ORCH_485.scd"
        ]
      }
    },
    {
      "source": [
        "00078",
        "DUD_078",
        "Weight of the World／Instrumental Version \\(From NieR:Automata\\)",
        "Weight of the World - Instrumental Version \\(From NieR:Automata\\)"
      ],
      "target": {
        "path": [
          "music/ex3/BGM_EX3_Ytc_24.scd",
          "music/ffxiv/Orchestrion/BGM_ORCH_486.scd"
        ]
      }
    },
    {
      "source": [
        "00079",
        "DUD_079",
        "遺サレタ場所／斜光 \\(From NieR:Automata\\)",
        "City Ruins - Rays of Light \\(From NieR:Automata\\)"
      ],
      "target": [
        {
          "path": "music/ex3/BGM_EX3_Ytc_12.scd"
        },
        {
          "path": [
            "music/ex3/BGM_EX3_Ytc_02.scd",
            "music/ffxiv/Orchestrion/BGM_ORCH_363.scd"
          ],
          "# comment": "Volume is a little bit lower than the above one.",
          "segments": [
            {
              "sourceFilters": {
                "source": "volume=-5dB"
              },
              "channels": [
                {
                  "source": "source",
                  "channel": 0
                },
                {
                  "source": "source",
                  "channel": 1
                }
              ]
            }
          ]
        }
      ]
    },
    {
      "source": [
        "00080",
        "DUD_080",
        "炎の七部族 ～黄金平原 パガルザン～",
        "Seven Flames"
      ],
      "target": {
        "path": [
          "music/ex3/BGM_EX3_Dan_D13.scd",
          "music/ffxiv/Orchestrion/BGM_ORCH_474.scd"
        ]
      }
    },
    {
      "source": [
        "00081",
        "DUD_081",
        "愛を求める者たち",
        "And Love You Shall Find"
      ],
      "target": {
        "path": [
          "music/ex3/BGM_EX3_Field_Welrit.scd",
          "music/ffxiv/Orchestrion/BGM_ORCH_475.scd"
        ]
      }
    },
    {
      "source": [
        "00082",
        "DUD_082",
        "孤児たちの戦い ～ダイヤウェポン捕獲作戦～",
        "In the Arms of War"
      ],
      "target": {
        "path": [
          "music/ex3/BGM_EX3_Ban_15.scd",
          "music/ffxiv/BGM_Ride_Dia.scd",
          "music/ffxiv/Orchestrion/BGM_ORCH_471.scd"
        ]
      }
    },
    {
      "source": [
        "00083",
        "DUD_083",
        "ひとりじゃない",
        "Forever at Your Side"
      ],
      "target": {
        "path": "music/ex3/BGM_EX3_Event_26.scd",
        "loopOffsetDelta": 6.426
      }
    },
    {
      "source": [
        "00084",
        "DUD_084",
        "魔導船 ～漆黒～",
        "Lunar Whale \\(Shadowbringers\\)"
      ],
      "target": {
        "path": "music/ffxiv/BGM_Ride_Fanfes2021.scd"
      }
    }
  ]
}